sdarray/__init__.py
sdarray-0.1.3.dist-info/LICENSE
sdarray-0.1.3.dist-info/WHEEL
sdarray-0.1.3.dist-info/METADATA
sdarray-0.1.3.dist-info/RECORD
