Metadata-Version: 2.1
Name: sdarray
Version: 0.1.3
Summary: Common single-dish data structure for radio astronomy
Home-page: https://github.com/sdarray/sdarray
License: MIT
Author: Akio Taniguchi
Author-email: taniguchi@a.phys.nagoya-u.ac.jp
Requires-Python: >=3.7,<3.10
Classifier: License :: OSI Approved :: MIT License
Classifier: Programming Language :: Python :: 3
Classifier: Programming Language :: Python :: 3.7
Classifier: Programming Language :: Python :: 3.8
Classifier: Programming Language :: Python :: 3.9
Project-URL: Documentation, https://sdarray.github.io/sdarray
